secret_key_database/__init__.py
secret_key_database/database.py
secret_key_database/encryption.py
secret_key_database/user.py
secret_key_database-0.1.3.dist-info/METADATA
secret_key_database-0.1.3.dist-info/WHEEL
secret_key_database-0.1.3.dist-info/top_level.txt
secret_key_database-0.1.3.dist-info/RECORD
