Metadata-Version: 2.4
Name: secret_key_database
Version: 0.1.3
Summary: A simple Python package for encrypting and decrypting secret keys.
Home-page: https://github.com/RichieHakim/secret_key_database
Author: Richard Hakim
License: LICENSE
Keywords: cryptography,encryption,security,secret_key_database
Requires-Dist: cryptography
Requires-Dist: pytest
Requires-Dist: hypothesis
Dynamic: author
Dynamic: description
Dynamic: description-content-type
Dynamic: home-page
Dynamic: keywords
Dynamic: license
Dynamic: requires-dist
Dynamic: summary
